django_docrootcms-3.6.dist-info/licenses/LICENSE
docrootcms/__init__.py
docrootcms/admin.py
docrootcms/apps.py
docrootcms/cms.py
docrootcms/forms.py
docrootcms/middleware.py
docrootcms/models.py
docrootcms/settings_utils.py
docrootcms/tests.py
docrootcms/urls.py
docrootcms/views.py
docrootcms/container_scripts/deploy.sh
docrootcms/container_scripts/docker-entrypoint.sh
docrootcms/container_scripts/install.sh
docrootcms/contrib/__init__.py
docrootcms/contrib/blog/__init__.py
docrootcms/contrib/blog/admin.py
docrootcms/contrib/blog/apps.py
docrootcms/contrib/blog/forms.py
docrootcms/contrib/blog/middleware.py
docrootcms/contrib/blog/models.py
docrootcms/contrib/blog/tests.py
docrootcms/contrib/blog/urls.py
docrootcms/contrib/blog/views.py
docrootcms/contrib/blog/migrations/0001_initial.py
docrootcms/contrib/blog/migrations/0002_auto_20201002_2035.py
docrootcms/contrib/blog/migrations/0004_bigauto_convert.py
docrootcms/contrib/blog/migrations/__init__.py
docrootcms/contrib/blog/templates/docrootcms_blog/index.html
docrootcms/contrib/blog/templates/docrootcms_blog/post_detail.html
docrootcms/contrib/blog/templates/markdownx/widget.html
docrootcms/contrib/blog/templatetags/conversions.py
docrootcms/contrib/blog/templatetags/__pycache__/conversions.cpython-310.pyc
docrootcms/install/files/favicon.ico
docrootcms/install/files/favicon.svg
docrootcms/install/files/robots.txt
docrootcms/install/files/robots_staging.txt
docrootcms/install/files/mdb/License.pdf
docrootcms/install/files/mdb/README.txt
docrootcms/install/files/mdb/Useful_Resources.pdf
docrootcms/install/files/mdb/index.html
docrootcms/install/files/mdb/css/bootstrap.css
docrootcms/install/files/mdb/css/bootstrap.min.css
docrootcms/install/files/mdb/css/mdb.css
docrootcms/install/files/mdb/css/mdb.lite.css
docrootcms/install/files/mdb/css/mdb.lite.min.css
docrootcms/install/files/mdb/css/mdb.lite.min.css.map
docrootcms/install/files/mdb/css/mdb.min.css
docrootcms/install/files/mdb/css/mdb.min.css.map
docrootcms/install/files/mdb/css/style.css
django_docrootcms-3.6.dist-info/METADATA
django_docrootcms-3.6.dist-info/WHEEL
django_docrootcms-3.6.dist-info/top_level.txt
django_docrootcms-3.6.dist-info/RECORD
